todo_mcp/__init__.py
todo_mcp/server.py
todo_mcp-0.1.0.dist-info/METADATA
todo_mcp-0.1.0.dist-info/WHEEL
todo_mcp-0.1.0.dist-info/entry_points.txt
todo_mcp-0.1.0.dist-info/RECORD
