Metadata-Version: 2.4
Name: todo-mcp
Version: 0.1.0
Summary: A MCP server project
Author-email: jyasuu <s1002605@pu.edu.tw>
Requires-Python: >=3.12
Requires-Dist: mcp>=1.6.0
Requires-Dist: requests
